.gitignore
.travis.yml
CHANGES.rst
CONTRIBUTORS.rst
MANIFEST.in
README.rst
bootstrap.py
buildout.cfg
checkouts.cfg
setup.py
travis.cfg
versions.cfg
docs/HISTORY.txt
docs/INSTALL.txt
docs/LICENSE.GPL
docs/LICENSE.txt
pretaweb/__init__.py
pretaweb.agls.egg-info/PKG-INFO
pretaweb.agls.egg-info/SOURCES.txt
pretaweb.agls.egg-info/dependency_links.txt
pretaweb.agls.egg-info/entry_points.txt
pretaweb.agls.egg-info/namespace_packages.txt
pretaweb.agls.egg-info/not-zip-safe
pretaweb.agls.egg-info/requires.txt
pretaweb.agls.egg-info/top_level.txt
pretaweb/agls/README.rst
pretaweb/agls/__init__.py
pretaweb/agls/config.py
pretaweb/agls/configure.zcml
pretaweb/agls/patches.py
pretaweb/agls/profiles.zcml
pretaweb/agls/setuphandlers.py
pretaweb/agls/behaviors/__init__.py
pretaweb/agls/behaviors/agls.py
pretaweb/agls/behaviors/configure.zcml
pretaweb/agls/browser/__init__.py
pretaweb/agls/browser/agls.py
pretaweb/agls/browser/configure.zcml
pretaweb/agls/browser/controlpanel.py
pretaweb/agls/browser/interfaces.py
pretaweb/agls/browser/viewlets.py
pretaweb/agls/browser/jbot/Products.CMFPlone.skins.plone_templates.rss_template.pt
pretaweb/agls/browser/resources/img/agls_icon.png
pretaweb/agls/browser/templates/agls.pt
pretaweb/agls/content/__init__.py
pretaweb/agls/content/agls.py
pretaweb/agls/content/configure.zcml
pretaweb/agls/form/__init__.py
pretaweb/agls/form/widget.py
pretaweb/agls/profiles/default/browserlayer.xml
pretaweb/agls/profiles/default/catalog.xml
pretaweb/agls/profiles/default/controlpanel.xml
pretaweb/agls/profiles/default/import_steps.xml
pretaweb/agls/profiles/default/metadata.xml
pretaweb/agls/profiles/default/portal_atct.xml
pretaweb/agls/profiles/default/pretaweb.agls.default.txt
pretaweb/agls/profiles/default/registry.xml
pretaweb/agls/profiles/default/skins.xml
pretaweb/agls/profiles/uninstall/browserlayer.xml
pretaweb/agls/profiles/uninstall/import_steps.xml
pretaweb/agls/profiles/uninstall/metadata.xml
pretaweb/agls/profiles/uninstall/pretaweb.agls.uninstall.txt
pretaweb/agls/skins/pretaweb_agls/multipleindexkeyword_widget.pt
pretaweb/agls/tests/__init__.py
pretaweb/agls/tests/base.py
pretaweb/agls/tests/test_doctest.py