Metadata-Version: 1.0
Name: pretaweb.agls
Version: 1.0.5
Summary: This package injects AGLS meta tags into Plone page.
Home-page: https://github.com/pretaweb/pretaweb.agls
Author: Dylan Jay
Author-email: software@pretaweb.com
License: GPL
Download-URL: https://github.com/pretaweb/pretaweb.agls/tarball/1.0.5
Keywords: plone agls metadata
Platform: UNKNOWN
Classifier: Framework :: Plone
Classifier: Intended Audience :: Developers
Classifier: License :: OSI Approved :: GNU General Public License (GPL)
